{
  "kind": "PodMetricsList",
  "apiVersion": "metrics.k8s.io/v1beta1",
  "metadata": {},
  "items": [
    {
      "metadata": {
        "name": "mysql-69c59fc7b-4zz8r",
        "namespace": "openfaas-fn",
        "creationTimestamp": "2025-05-25T21:57:06Z",
        "labels": {
          "app": "mysql",
          "pod-template-hash": "69c59fc7b"
        }
      },
      "timestamp": "2025-05-25T21:56:52Z",
      "window": "10.4s",
      "containers": [
        {
          "name": "mysql",
          "usage": {
            "cpu": "318612211n",
            "memory": "488688Ki"
          }
        }
      ]
    },
    {
      "metadata": {
        "name": "product-purchase-7c996bc5d5-984pp",
        "namespace": "openfaas-fn",
        "creationTimestamp": "2025-05-25T21:57:06Z",
        "labels": {
          "com.openfaas.scale.factor": "10",
          "com.openfaas.scale.max": "5",
          "com.openfaas.scale.min": "1",
          "faas_function": "product-purchase",
          "pod-template-hash": "7c996bc5d5"
        }
      },
      "timestamp": "2025-05-25T21:56:55Z",
      "window": "13.306s",
      "containers": [
        {
          "name": "product-purchase",
          "usage": {
            "cpu": "262884037n",
            "memory": "78068Ki"
          }
        }
      ]
    },
    {
      "metadata": {
        "name": "product-purchase-7c996bc5d5-bm6lp",
        "namespace": "openfaas-fn",
        "creationTimestamp": "2025-05-25T21:57:06Z",
        "labels": {
          "com.openfaas.scale.factor": "10",
          "com.openfaas.scale.max": "5",
          "com.openfaas.scale.min": "1",
          "faas_function": "product-purchase",
          "pod-template-hash": "7c996bc5d5"
        }
      },
      "timestamp": "2025-05-25T21:56:44Z",
      "window": "12.084s",
      "containers": [
        {
          "name": "product-purchase",
          "usage": {
            "cpu": "276281281n",
            "memory": "77704Ki"
          }
        }
      ]
    },
    {
      "metadata": {
        "name": "product-purchase-7c996bc5d5-d4bcl",
        "namespace": "openfaas-fn",
        "creationTimestamp": "2025-05-25T21:57:06Z",
        "labels": {
          "com.openfaas.scale.factor": "10",
          "com.openfaas.scale.max": "5",
          "com.openfaas.scale.min": "1",
          "faas_function": "product-purchase",
          "pod-template-hash": "7c996bc5d5"
        }
      },
      "timestamp": "2025-05-25T21:56:44Z",
      "window": "16.779s",
      "containers": [
        {
          "name": "product-purchase",
          "usage": {
            "cpu": "255272125n",
            "memory": "79508Ki"
          }
        }
      ]
    },
    {
      "metadata": {
        "name": "product-purchase-7c996bc5d5-h8gtx",
        "namespace": "openfaas-fn",
        "creationTimestamp": "2025-05-25T21:57:06Z",
        "labels": {
          "com.openfaas.scale.factor": "10",
          "com.openfaas.scale.max": "5",
          "com.openfaas.scale.min": "1",
          "faas_function": "product-purchase",
          "pod-template-hash": "7c996bc5d5"
        }
      },
      "timestamp": "2025-05-25T21:56:48Z",
      "window": "16.695s",
      "containers": [
        {
          "name": "product-purchase",
          "usage": {
            "cpu": "260378376n",
            "memory": "79180Ki"
          }
        }
      ]
    },
    {
      "metadata": {
        "name": "product-purchase-7c996bc5d5-lmq7m",
        "namespace": "openfaas-fn",
        "creationTimestamp": "2025-05-25T21:57:06Z",
        "labels": {
          "com.openfaas.scale.factor": "10",
          "com.openfaas.scale.max": "5",
          "com.openfaas.scale.min": "1",
          "faas_function": "product-purchase",
          "pod-template-hash": "7c996bc5d5"
        }
      },
      "timestamp": "2025-05-25T21:56:46Z",
      "window": "12.294s",
      "containers": [
        {
          "name": "product-purchase",
          "usage": {
            "cpu": "265116316n",
            "memory": "78584Ki"
          }
        }
      ]
    },
    {
      "metadata": {
        "name": "product-purchase-authenticate-566d665777-s4n47",
        "namespace": "openfaas-fn",
        "creationTimestamp": "2025-05-25T21:57:06Z",
        "labels": {
          "com.openfaas.scale.factor": "10",
          "com.openfaas.scale.max": "5",
          "com.openfaas.scale.min": "1",
          "faas_function": "product-purchase-authenticate",
          "pod-template-hash": "566d665777"
        }
      },
      "timestamp": "2025-05-25T21:56:52Z",
      "window": "14.868s",
      "containers": [
        {
          "name": "product-purchase-authenticate",
          "usage": {
            "cpu": "785647n",
            "memory": "20388Ki"
          }
        }
      ]
    },
    {
      "metadata": {
        "name": "product-purchase-authorize-cc-656b5b8c4-6d8xq",
        "namespace": "openfaas-fn",
        "creationTimestamp": "2025-05-25T21:57:06Z",
        "labels": {
          "com.openfaas.scale.factor": "10",
          "com.openfaas.scale.max": "5",
          "com.openfaas.scale.min": "1",
          "faas_function": "product-purchase-authorize-cc",
          "pod-template-hash": "656b5b8c4"
        }
      },
      "timestamp": "2025-05-25T21:56:46Z",
      "window": "14.37s",
      "containers": [
        {
          "name": "product-purchase-authorize-cc",
          "usage": {
            "cpu": "239752609n",
            "memory": "73152Ki"
          }
        }
      ]
    },
    {
      "metadata": {
        "name": "product-purchase-authorize-cc-656b5b8c4-lzqzm",
        "namespace": "openfaas-fn",
        "creationTimestamp": "2025-05-25T21:57:06Z",
        "labels": {
          "com.openfaas.scale.factor": "10",
          "com.openfaas.scale.max": "5",
          "com.openfaas.scale.min": "1",
          "faas_function": "product-purchase-authorize-cc",
          "pod-template-hash": "656b5b8c4"
        }
      },
      "timestamp": "2025-05-25T21:56:56Z",
      "window": "16.493s",
      "containers": [
        {
          "name": "product-purchase-authorize-cc",
          "usage": {
            "cpu": "250772570n",
            "memory": "71676Ki"
          }
        }
      ]
    },
    {
      "metadata": {
        "name": "product-purchase-authorize-cc-656b5b8c4-nqpjk",
        "namespace": "openfaas-fn",
        "creationTimestamp": "2025-05-25T21:57:06Z",
        "labels": {
          "com.openfaas.scale.factor": "10",
          "com.openfaas.scale.max": "5",
          "com.openfaas.scale.min": "1",
          "faas_function": "product-purchase-authorize-cc",
          "pod-template-hash": "656b5b8c4"
        }
      },
      "timestamp": "2025-05-25T21:56:52Z",
      "window": "12.271s",
      "containers": [
        {
          "name": "product-purchase-authorize-cc",
          "usage": {
            "cpu": "235409909n",
            "memory": "73868Ki"
          }
        }
      ]
    },
    {
      "metadata": {
        "name": "product-purchase-authorize-cc-656b5b8c4-qnj58",
        "namespace": "openfaas-fn",
        "creationTimestamp": "2025-05-25T21:57:06Z",
        "labels": {
          "com.openfaas.scale.factor": "10",
          "com.openfaas.scale.max": "5",
          "com.openfaas.scale.min": "1",
          "faas_function": "product-purchase-authorize-cc",
          "pod-template-hash": "656b5b8c4"
        }
      },
      "timestamp": "2025-05-25T21:56:54Z",
      "window": "28.326s",
      "containers": [
        {
          "name": "product-purchase-authorize-cc",
          "usage": {
            "cpu": "247698792n",
            "memory": "72980Ki"
          }
        }
      ]
    },
    {
      "metadata": {
        "name": "product-purchase-authorize-cc-656b5b8c4-snrml",
        "namespace": "openfaas-fn",
        "creationTimestamp": "2025-05-25T21:57:06Z",
        "labels": {
          "com.openfaas.scale.factor": "10",
          "com.openfaas.scale.max": "5",
          "com.openfaas.scale.min": "1",
          "faas_function": "product-purchase-authorize-cc",
          "pod-template-hash": "656b5b8c4"
        }
      },
      "timestamp": "2025-05-25T21:56:48Z",
      "window": "12.545s",
      "containers": [
        {
          "name": "product-purchase-authorize-cc",
          "usage": {
            "cpu": "258481626n",
            "memory": "75476Ki"
          }
        }
      ]
    },
    {
      "metadata": {
        "name": "product-purchase-get-price-79fc94c69f-77ncw",
        "namespace": "openfaas-fn",
        "creationTimestamp": "2025-05-25T21:57:06Z",
        "labels": {
          "com.openfaas.scale.factor": "10",
          "com.openfaas.scale.max": "5",
          "com.openfaas.scale.min": "1",
          "faas_function": "product-purchase-get-price",
          "pod-template-hash": "79fc94c69f"
        }
      },
      "timestamp": "2025-05-25T21:56:48Z",
      "window": "10.899s",
      "containers": [
        {
          "name": "product-purchase-get-price",
          "usage": {
            "cpu": "277523075n",
            "memory": "75028Ki"
          }
        }
      ]
    },
    {
      "metadata": {
        "name": "product-purchase-get-price-79fc94c69f-fljnk",
        "namespace": "openfaas-fn",
        "creationTimestamp": "2025-05-25T21:57:06Z",
        "labels": {
          "com.openfaas.scale.factor": "10",
          "com.openfaas.scale.max": "5",
          "com.openfaas.scale.min": "1",
          "faas_function": "product-purchase-get-price",
          "pod-template-hash": "79fc94c69f"
        }
      },
      "timestamp": "2025-05-25T21:56:46Z",
      "window": "15.414s",
      "containers": [
        {
          "name": "product-purchase-get-price",
          "usage": {
            "cpu": "228531140n",
            "memory": "73468Ki"
          }
        }
      ]
    },
    {
      "metadata": {
        "name": "product-purchase-get-price-79fc94c69f-rdmf6",
        "namespace": "openfaas-fn",
        "creationTimestamp": "2025-05-25T21:57:06Z",
        "labels": {
          "com.openfaas.scale.factor": "10",
          "com.openfaas.scale.max": "5",
          "com.openfaas.scale.min": "1",
          "faas_function": "product-purchase-get-price",
          "pod-template-hash": "79fc94c69f"
        }
      },
      "timestamp": "2025-05-25T21:56:51Z",
      "window": "15.515s",
      "containers": [
        {
          "name": "product-purchase-get-price",
          "usage": {
            "cpu": "280676377n",
            "memory": "73Mi"
          }
        }
      ]
    },
    {
      "metadata": {
        "name": "product-purchase-get-price-79fc94c69f-xtsnf",
        "namespace": "openfaas-fn",
        "creationTimestamp": "2025-05-25T21:57:06Z",
        "labels": {
          "com.openfaas.scale.factor": "10",
          "com.openfaas.scale.max": "5",
          "com.openfaas.scale.min": "1",
          "faas_function": "product-purchase-get-price",
          "pod-template-hash": "79fc94c69f"
        }
      },
      "timestamp": "2025-05-25T21:56:51Z",
      "window": "17.671s",
      "containers": [
        {
          "name": "product-purchase-get-price",
          "usage": {
            "cpu": "265013694n",
            "memory": "74800Ki"
          }
        }
      ]
    },
    {
      "metadata": {
        "name": "product-purchase-get-price-79fc94c69f-z2fvp",
        "namespace": "openfaas-fn",
        "creationTimestamp": "2025-05-25T21:57:06Z",
        "labels": {
          "com.openfaas.scale.factor": "10",
          "com.openfaas.scale.max": "5",
          "com.openfaas.scale.min": "1",
          "faas_function": "product-purchase-get-price",
          "pod-template-hash": "79fc94c69f"
        }
      },
      "timestamp": "2025-05-25T21:56:53Z",
      "window": "14.334s",
      "containers": [
        {
          "name": "product-purchase-get-price",
          "usage": {
            "cpu": "239101995n",
            "memory": "73692Ki"
          }
        }
      ]
    },
    {
      "metadata": {
        "name": "product-purchase-publish-565b7d9d4d-7c2ln",
        "namespace": "openfaas-fn",
        "creationTimestamp": "2025-05-25T21:57:06Z",
        "labels": {
          "com.openfaas.scale.factor": "10",
          "com.openfaas.scale.max": "5",
          "com.openfaas.scale.min": "1",
          "faas_function": "product-purchase-publish",
          "pod-template-hash": "565b7d9d4d"
        }
      },
      "timestamp": "2025-05-25T21:56:50Z",
      "window": "17.618s",
      "containers": [
        {
          "name": "product-purchase-publish",
          "usage": {
            "cpu": "67468952n",
            "memory": "37420Ki"
          }
        }
      ]
    },
    {
      "metadata": {
        "name": "product-purchase-publish-565b7d9d4d-7v7qk",
        "namespace": "openfaas-fn",
        "creationTimestamp": "2025-05-25T21:57:06Z",
        "labels": {
          "com.openfaas.scale.factor": "10",
          "com.openfaas.scale.max": "5",
          "com.openfaas.scale.min": "1",
          "faas_function": "product-purchase-publish",
          "pod-template-hash": "565b7d9d4d"
        }
      },
      "timestamp": "2025-05-25T21:56:53Z",
      "window": "10.688s",
      "containers": [
        {
          "name": "product-purchase-publish",
          "usage": {
            "cpu": "58264689n",
            "memory": "34Mi"
          }
        }
      ]
    },
    {
      "metadata": {
        "name": "product-purchase-publish-565b7d9d4d-kj2t7",
        "namespace": "openfaas-fn",
        "creationTimestamp": "2025-05-25T21:57:06Z",
        "labels": {
          "com.openfaas.scale.factor": "10",
          "com.openfaas.scale.max": "5",
          "com.openfaas.scale.min": "1",
          "faas_function": "product-purchase-publish",
          "pod-template-hash": "565b7d9d4d"
        }
      },
      "timestamp": "2025-05-25T21:56:54Z",
      "window": "15.834s",
      "containers": [
        {
          "name": "product-purchase-publish",
          "usage": {
            "cpu": "75275419n",
            "memory": "36780Ki"
          }
        }
      ]
    },
    {
      "metadata": {
        "name": "product-purchase-publish-565b7d9d4d-lvz48",
        "namespace": "openfaas-fn",
        "creationTimestamp": "2025-05-25T21:57:06Z",
        "labels": {
          "com.openfaas.scale.factor": "10",
          "com.openfaas.scale.max": "5",
          "com.openfaas.scale.min": "1",
          "faas_function": "product-purchase-publish",
          "pod-template-hash": "565b7d9d4d"
        }
      },
      "timestamp": "2025-05-25T21:56:48Z",
      "window": "16.638s",
      "containers": [
        {
          "name": "product-purchase-publish",
          "usage": {
            "cpu": "63804002n",
            "memory": "35480Ki"
          }
        }
      ]
    },
    {
      "metadata": {
        "name": "product-purchase-publish-565b7d9d4d-zsmgv",
        "namespace": "openfaas-fn",
        "creationTimestamp": "2025-05-25T21:57:06Z",
        "labels": {
          "com.openfaas.scale.factor": "10",
          "com.openfaas.scale.max": "5",
          "com.openfaas.scale.min": "1",
          "faas_function": "product-purchase-publish",
          "pod-template-hash": "565b7d9d4d"
        }
      },
      "timestamp": "2025-05-25T21:56:53Z",
      "window": "14.62s",
      "containers": [
        {
          "name": "product-purchase-publish",
          "usage": {
            "cpu": "74255677n",
            "memory": "38Mi"
          }
        }
      ]
    }
  ]
}
