{
  "kind": "PodMetricsList",
  "apiVersion": "metrics.k8s.io/v1beta1",
  "metadata": {},
  "items": [
    {
      "metadata": {
        "name": "mysql-69c59fc7b-4zz8r",
        "namespace": "openfaas-fn",
        "creationTimestamp": "2025-05-25T21:44:10Z",
        "labels": {
          "app": "mysql",
          "pod-template-hash": "69c59fc7b"
        }
      },
      "timestamp": "2025-05-25T21:43:54Z",
      "window": "30.011s",
      "containers": [
        {
          "name": "mysql",
          "usage": {
            "cpu": "333581586n",
            "memory": "488780Ki"
          }
        }
      ]
    },
    {
      "metadata": {
        "name": "product-purchase-authenticate-68d8fcd9b6-8wjvn",
        "namespace": "openfaas-fn",
        "creationTimestamp": "2025-05-25T21:44:10Z",
        "labels": {
          "com.openfaas.scale.factor": "10",
          "com.openfaas.scale.max": "5",
          "com.openfaas.scale.min": "1",
          "faas_function": "product-purchase-authenticate",
          "pod-template-hash": "68d8fcd9b6"
        }
      },
      "timestamp": "2025-05-25T21:43:44Z",
      "window": "18.083s",
      "containers": [
        {
          "name": "product-purchase-authenticate",
          "usage": {
            "cpu": "1063927n",
            "memory": "57432Ki"
          }
        }
      ]
    },
    {
      "metadata": {
        "name": "product-purchase-authorize-cc-5b9fdfbc55-8ntlm",
        "namespace": "openfaas-fn",
        "creationTimestamp": "2025-05-25T21:44:10Z",
        "labels": {
          "com.openfaas.scale.factor": "10",
          "com.openfaas.scale.max": "5",
          "com.openfaas.scale.min": "1",
          "faas_function": "product-purchase-authorize-cc",
          "pod-template-hash": "5b9fdfbc55"
        }
      },
      "timestamp": "2025-05-25T21:43:49Z",
      "window": "15.272s",
      "containers": [
        {
          "name": "product-purchase-authorize-cc",
          "usage": {
            "cpu": "667971712n",
            "memory": "119184Ki"
          }
        }
      ]
    },
    {
      "metadata": {
        "name": "product-purchase-authorize-cc-5b9fdfbc55-9w2v6",
        "namespace": "openfaas-fn",
        "creationTimestamp": "2025-05-25T21:44:10Z",
        "labels": {
          "com.openfaas.scale.factor": "10",
          "com.openfaas.scale.max": "5",
          "com.openfaas.scale.min": "1",
          "faas_function": "product-purchase-authorize-cc",
          "pod-template-hash": "5b9fdfbc55"
        }
      },
      "timestamp": "2025-05-25T21:43:52Z",
      "window": "16.4s",
      "containers": [
        {
          "name": "product-purchase-authorize-cc",
          "usage": {
            "cpu": "459163109n",
            "memory": "114912Ki"
          }
        }
      ]
    },
    {
      "metadata": {
        "name": "product-purchase-authorize-cc-5b9fdfbc55-f8t5k",
        "namespace": "openfaas-fn",
        "creationTimestamp": "2025-05-25T21:44:10Z",
        "labels": {
          "com.openfaas.scale.factor": "10",
          "com.openfaas.scale.max": "5",
          "com.openfaas.scale.min": "1",
          "faas_function": "product-purchase-authorize-cc",
          "pod-template-hash": "5b9fdfbc55"
        }
      },
      "timestamp": "2025-05-25T21:43:50Z",
      "window": "16.169s",
      "containers": [
        {
          "name": "product-purchase-authorize-cc",
          "usage": {
            "cpu": "541493413n",
            "memory": "119592Ki"
          }
        }
      ]
    },
    {
      "metadata": {
        "name": "product-purchase-authorize-cc-5b9fdfbc55-ndhtd",
        "namespace": "openfaas-fn",
        "creationTimestamp": "2025-05-25T21:44:10Z",
        "labels": {
          "com.openfaas.scale.factor": "10",
          "com.openfaas.scale.max": "5",
          "com.openfaas.scale.min": "1",
          "faas_function": "product-purchase-authorize-cc",
          "pod-template-hash": "5b9fdfbc55"
        }
      },
      "timestamp": "2025-05-25T21:43:56Z",
      "window": "16.202s",
      "containers": [
        {
          "name": "product-purchase-authorize-cc",
          "usage": {
            "cpu": "537537464n",
            "memory": "123592Ki"
          }
        }
      ]
    },
    {
      "metadata": {
        "name": "product-purchase-authorize-cc-5b9fdfbc55-wbnvh",
        "namespace": "openfaas-fn",
        "creationTimestamp": "2025-05-25T21:44:10Z",
        "labels": {
          "com.openfaas.scale.factor": "10",
          "com.openfaas.scale.max": "5",
          "com.openfaas.scale.min": "1",
          "faas_function": "product-purchase-authorize-cc",
          "pod-template-hash": "5b9fdfbc55"
        }
      },
      "timestamp": "2025-05-25T21:43:41Z",
      "window": "23.111s",
      "containers": [
        {
          "name": "product-purchase-authorize-cc",
          "usage": {
            "cpu": "822816537n",
            "memory": "121324Ki"
          }
        }
      ]
    },
    {
      "metadata": {
        "name": "product-purchase-f667566f4-75mvc",
        "namespace": "openfaas-fn",
        "creationTimestamp": "2025-05-25T21:44:10Z",
        "labels": {
          "com.openfaas.scale.factor": "10",
          "com.openfaas.scale.max": "5",
          "com.openfaas.scale.min": "1",
          "faas_function": "product-purchase",
          "pod-template-hash": "f667566f4"
        }
      },
      "timestamp": "2025-05-25T21:43:52Z",
      "window": "14.316s",
      "containers": [
        {
          "name": "product-purchase",
          "usage": {
            "cpu": "949018720n",
            "memory": "130412Ki"
          }
        }
      ]
    },
    {
      "metadata": {
        "name": "product-purchase-f667566f4-k6mvp",
        "namespace": "openfaas-fn",
        "creationTimestamp": "2025-05-25T21:44:10Z",
        "labels": {
          "com.openfaas.scale.factor": "10",
          "com.openfaas.scale.max": "5",
          "com.openfaas.scale.min": "1",
          "faas_function": "product-purchase",
          "pod-template-hash": "f667566f4"
        }
      },
      "timestamp": "2025-05-25T21:43:46Z",
      "window": "16.316s",
      "containers": [
        {
          "name": "product-purchase",
          "usage": {
            "cpu": "903799889n",
            "memory": "133580Ki"
          }
        }
      ]
    },
    {
      "metadata": {
        "name": "product-purchase-f667566f4-lgv2v",
        "namespace": "openfaas-fn",
        "creationTimestamp": "2025-05-25T21:44:10Z",
        "labels": {
          "com.openfaas.scale.factor": "10",
          "com.openfaas.scale.max": "5",
          "com.openfaas.scale.min": "1",
          "faas_function": "product-purchase",
          "pod-template-hash": "f667566f4"
        }
      },
      "timestamp": "2025-05-25T21:43:49Z",
      "window": "11.731s",
      "containers": [
        {
          "name": "product-purchase",
          "usage": {
            "cpu": "764824396n",
            "memory": "135504Ki"
          }
        }
      ]
    },
    {
      "metadata": {
        "name": "product-purchase-f667566f4-nsfx2",
        "namespace": "openfaas-fn",
        "creationTimestamp": "2025-05-25T21:44:10Z",
        "labels": {
          "com.openfaas.scale.factor": "10",
          "com.openfaas.scale.max": "5",
          "com.openfaas.scale.min": "1",
          "faas_function": "product-purchase",
          "pod-template-hash": "f667566f4"
        }
      },
      "timestamp": "2025-05-25T21:43:42Z",
      "window": "17.963s",
      "containers": [
        {
          "name": "product-purchase",
          "usage": {
            "cpu": "808220842n",
            "memory": "146160Ki"
          }
        }
      ]
    },
    {
      "metadata": {
        "name": "product-purchase-f667566f4-zlhs9",
        "namespace": "openfaas-fn",
        "creationTimestamp": "2025-05-25T21:44:10Z",
        "labels": {
          "com.openfaas.scale.factor": "10",
          "com.openfaas.scale.max": "5",
          "com.openfaas.scale.min": "1",
          "faas_function": "product-purchase",
          "pod-template-hash": "f667566f4"
        }
      },
      "timestamp": "2025-05-25T21:43:46Z",
      "window": "17.902s",
      "containers": [
        {
          "name": "product-purchase",
          "usage": {
            "cpu": "536811361n",
            "memory": "150032Ki"
          }
        }
      ]
    },
    {
      "metadata": {
        "name": "product-purchase-get-price-6bbc499cc8-jjs4s",
        "namespace": "openfaas-fn",
        "creationTimestamp": "2025-05-25T21:44:10Z",
        "labels": {
          "com.openfaas.scale.factor": "10",
          "com.openfaas.scale.max": "5",
          "com.openfaas.scale.min": "1",
          "faas_function": "product-purchase-get-price",
          "pod-template-hash": "6bbc499cc8"
        }
      },
      "timestamp": "2025-05-25T21:43:52Z",
      "window": "15.758s",
      "containers": [
        {
          "name": "product-purchase-get-price",
          "usage": {
            "cpu": "651441616n",
            "memory": "119064Ki"
          }
        }
      ]
    },
    {
      "metadata": {
        "name": "product-purchase-get-price-6bbc499cc8-mhtww",
        "namespace": "openfaas-fn",
        "creationTimestamp": "2025-05-25T21:44:10Z",
        "labels": {
          "com.openfaas.scale.factor": "10",
          "com.openfaas.scale.max": "5",
          "com.openfaas.scale.min": "1",
          "faas_function": "product-purchase-get-price",
          "pod-template-hash": "6bbc499cc8"
        }
      },
      "timestamp": "2025-05-25T21:43:55Z",
      "window": "17.632s",
      "containers": [
        {
          "name": "product-purchase-get-price",
          "usage": {
            "cpu": "689618591n",
            "memory": "120044Ki"
          }
        }
      ]
    },
    {
      "metadata": {
        "name": "product-purchase-get-price-6bbc499cc8-t5bp4",
        "namespace": "openfaas-fn",
        "creationTimestamp": "2025-05-25T21:44:10Z",
        "labels": {
          "com.openfaas.scale.factor": "10",
          "com.openfaas.scale.max": "5",
          "com.openfaas.scale.min": "1",
          "faas_function": "product-purchase-get-price",
          "pod-template-hash": "6bbc499cc8"
        }
      },
      "timestamp": "2025-05-25T21:43:55Z",
      "window": "18.15s",
      "containers": [
        {
          "name": "product-purchase-get-price",
          "usage": {
            "cpu": "627810633n",
            "memory": "121992Ki"
          }
        }
      ]
    },
    {
      "metadata": {
        "name": "product-purchase-get-price-6bbc499cc8-wc6wv",
        "namespace": "openfaas-fn",
        "creationTimestamp": "2025-05-25T21:44:10Z",
        "labels": {
          "com.openfaas.scale.factor": "10",
          "com.openfaas.scale.max": "5",
          "com.openfaas.scale.min": "1",
          "faas_function": "product-purchase-get-price",
          "pod-template-hash": "6bbc499cc8"
        }
      },
      "timestamp": "2025-05-25T21:43:55Z",
      "window": "14.804s",
      "containers": [
        {
          "name": "product-purchase-get-price",
          "usage": {
            "cpu": "619136517n",
            "memory": "118448Ki"
          }
        }
      ]
    },
    {
      "metadata": {
        "name": "product-purchase-get-price-6bbc499cc8-zst5d",
        "namespace": "openfaas-fn",
        "creationTimestamp": "2025-05-25T21:44:10Z",
        "labels": {
          "com.openfaas.scale.factor": "10",
          "com.openfaas.scale.max": "5",
          "com.openfaas.scale.min": "1",
          "faas_function": "product-purchase-get-price",
          "pod-template-hash": "6bbc499cc8"
        }
      },
      "timestamp": "2025-05-25T21:43:48Z",
      "window": "18.458s",
      "containers": [
        {
          "name": "product-purchase-get-price",
          "usage": {
            "cpu": "387798298n",
            "memory": "118396Ki"
          }
        }
      ]
    },
    {
      "metadata": {
        "name": "product-purchase-publish-5d9566f989-4tzn5",
        "namespace": "openfaas-fn",
        "creationTimestamp": "2025-05-25T21:44:10Z",
        "labels": {
          "com.openfaas.scale.factor": "10",
          "com.openfaas.scale.max": "5",
          "com.openfaas.scale.min": "1",
          "faas_function": "product-purchase-publish",
          "pod-template-hash": "5d9566f989"
        }
      },
      "timestamp": "2025-05-25T21:43:51Z",
      "window": "10.364s",
      "containers": [
        {
          "name": "product-purchase-publish",
          "usage": {
            "cpu": "320391837n",
            "memory": "107992Ki"
          }
        }
      ]
    },
    {
      "metadata": {
        "name": "product-purchase-publish-5d9566f989-9797b",
        "namespace": "openfaas-fn",
        "creationTimestamp": "2025-05-25T21:44:10Z",
        "labels": {
          "com.openfaas.scale.factor": "10",
          "com.openfaas.scale.max": "5",
          "com.openfaas.scale.min": "1",
          "faas_function": "product-purchase-publish",
          "pod-template-hash": "5d9566f989"
        }
      },
      "timestamp": "2025-05-25T21:43:50Z",
      "window": "13.022s",
      "containers": [
        {
          "name": "product-purchase-publish",
          "usage": {
            "cpu": "182004223n",
            "memory": "85820Ki"
          }
        }
      ]
    },
    {
      "metadata": {
        "name": "product-purchase-publish-5d9566f989-dxggm",
        "namespace": "openfaas-fn",
        "creationTimestamp": "2025-05-25T21:44:10Z",
        "labels": {
          "com.openfaas.scale.factor": "10",
          "com.openfaas.scale.max": "5",
          "com.openfaas.scale.min": "1",
          "faas_function": "product-purchase-publish",
          "pod-template-hash": "5d9566f989"
        }
      },
      "timestamp": "2025-05-25T21:43:51Z",
      "window": "11.925s",
      "containers": [
        {
          "name": "product-purchase-publish",
          "usage": {
            "cpu": "71933584n",
            "memory": "114868Ki"
          }
        }
      ]
    },
    {
      "metadata": {
        "name": "product-purchase-publish-5d9566f989-kqxxp",
        "namespace": "openfaas-fn",
        "creationTimestamp": "2025-05-25T21:44:10Z",
        "labels": {
          "com.openfaas.scale.factor": "10",
          "com.openfaas.scale.max": "5",
          "com.openfaas.scale.min": "1",
          "faas_function": "product-purchase-publish",
          "pod-template-hash": "5d9566f989"
        }
      },
      "timestamp": "2025-05-25T21:43:50Z",
      "window": "16.274s",
      "containers": [
        {
          "name": "product-purchase-publish",
          "usage": {
            "cpu": "73221273n",
            "memory": "81704Ki"
          }
        }
      ]
    },
    {
      "metadata": {
        "name": "product-purchase-publish-5d9566f989-zzch9",
        "namespace": "openfaas-fn",
        "creationTimestamp": "2025-05-25T21:44:10Z",
        "labels": {
          "com.openfaas.scale.factor": "10",
          "com.openfaas.scale.max": "5",
          "com.openfaas.scale.min": "1",
          "faas_function": "product-purchase-publish",
          "pod-template-hash": "5d9566f989"
        }
      },
      "timestamp": "2025-05-25T21:43:51Z",
      "window": "15.381s",
      "containers": [
        {
          "name": "product-purchase-publish",
          "usage": {
            "cpu": "297838892n",
            "memory": "94900Ki"
          }
        }
      ]
    }
  ]
}
