{
  "kind": "PodMetricsList",
  "apiVersion": "metrics.k8s.io/v1beta1",
  "metadata": {},
  "items": [
    {
      "metadata": {
        "name": "mysql-69c59fc7b-4zz8r",
        "namespace": "openfaas-fn",
        "creationTimestamp": "2025-05-25T21:37:01Z",
        "labels": {
          "app": "mysql",
          "pod-template-hash": "69c59fc7b"
        }
      },
      "timestamp": "2025-05-25T21:36:57Z",
      "window": "16.869s",
      "containers": [
        {
          "name": "mysql",
          "usage": {
            "cpu": "19123243n",
            "memory": "488712Ki"
          }
        }
      ]
    },
    {
      "metadata": {
        "name": "product-purchase-authenticate-68d8fcd9b6-8wjvn",
        "namespace": "openfaas-fn",
        "creationTimestamp": "2025-05-25T21:37:01Z",
        "labels": {
          "com.openfaas.scale.factor": "10",
          "com.openfaas.scale.max": "5",
          "com.openfaas.scale.min": "1",
          "faas_function": "product-purchase-authenticate",
          "pod-template-hash": "68d8fcd9b6"
        }
      },
      "timestamp": "2025-05-25T21:36:53Z",
      "window": "17.304s",
      "containers": [
        {
          "name": "product-purchase-authenticate",
          "usage": {
            "cpu": "1130316n",
            "memory": "56028Ki"
          }
        }
      ]
    },
    {
      "metadata": {
        "name": "product-purchase-authorize-cc-5b9fdfbc55-ndhtd",
        "namespace": "openfaas-fn",
        "creationTimestamp": "2025-05-25T21:37:01Z",
        "labels": {
          "com.openfaas.scale.factor": "10",
          "com.openfaas.scale.max": "5",
          "com.openfaas.scale.min": "1",
          "faas_function": "product-purchase-authorize-cc",
          "pod-template-hash": "5b9fdfbc55"
        }
      },
      "timestamp": "2025-05-25T21:36:47Z",
      "window": "13.624s",
      "containers": [
        {
          "name": "product-purchase-authorize-cc",
          "usage": {
            "cpu": "1211685n",
            "memory": "56172Ki"
          }
        }
      ]
    },
    {
      "metadata": {
        "name": "product-purchase-f667566f4-75mvc",
        "namespace": "openfaas-fn",
        "creationTimestamp": "2025-05-25T21:37:01Z",
        "labels": {
          "com.openfaas.scale.factor": "10",
          "com.openfaas.scale.max": "5",
          "com.openfaas.scale.min": "1",
          "faas_function": "product-purchase",
          "pod-template-hash": "f667566f4"
        }
      },
      "timestamp": "2025-05-25T21:36:54Z",
      "window": "18.592s",
      "containers": [
        {
          "name": "product-purchase",
          "usage": {
            "cpu": "329327506n",
            "memory": "78144Ki"
          }
        }
      ]
    },
    {
      "metadata": {
        "name": "product-purchase-get-price-6bbc499cc8-t5bp4",
        "namespace": "openfaas-fn",
        "creationTimestamp": "2025-05-25T21:37:01Z",
        "labels": {
          "com.openfaas.scale.factor": "10",
          "com.openfaas.scale.max": "5",
          "com.openfaas.scale.min": "1",
          "faas_function": "product-purchase-get-price",
          "pod-template-hash": "6bbc499cc8"
        }
      },
      "timestamp": "2025-05-25T21:36:55Z",
      "window": "21.85s",
      "containers": [
        {
          "name": "product-purchase-get-price",
          "usage": {
            "cpu": "331461418n",
            "memory": "76260Ki"
          }
        }
      ]
    },
    {
      "metadata": {
        "name": "product-purchase-publish-5d9566f989-kqxxp",
        "namespace": "openfaas-fn",
        "creationTimestamp": "2025-05-25T21:37:01Z",
        "labels": {
          "com.openfaas.scale.factor": "10",
          "com.openfaas.scale.max": "5",
          "com.openfaas.scale.min": "1",
          "faas_function": "product-purchase-publish",
          "pod-template-hash": "5d9566f989"
        }
      },
      "timestamp": "2025-05-25T21:36:47Z",
      "window": "13.65s",
      "containers": [
        {
          "name": "product-purchase-publish",
          "usage": {
            "cpu": "1210402n",
            "memory": "53040Ki"
          }
        }
      ]
    }
  ]
}
